{
  "dashboard": {
    "id": null,
    "title": "Science Map Platform",
    "tags": ["science-map", "microservices"],
    "style": "dark",
    "timezone": "browser",
    "panels": [
      {
        "id": 1,
        "title": "HTTP Requests Total",
        "type": "stat",
        "targets": [
          {
            "expr": "sum(rate(api_gateway_http_requests_total[5m]))",
            "legendFormat": "API Gateway"
          },
          {
            "expr": "sum(rate(auth_service_http_requests_total[5m]))",
            "legendFormat": "Auth Service"
          },
          {
            "expr": "sum(rate(graph_service_http_requests_total[5m]))",
            "legendFormat": "Graph Service"
          },
          {
            "expr": "sum(rate(search_service_http_requests_total[5m]))",
            "legendFormat": "Search Service"
          },
          {
            "expr": "sum(rate(jobs_service_http_requests_total[5m]))",
            "legendFormat": "Jobs Service"
          }
        ],
        "gridPos": {"h": 8, "w": 12, "x": 0, "y": 0}
      },
      {
        "id": 2,
        "title": "Service Health Status",
        "type": "table",
        "targets": [
          {
            "expr": "up{job=~\"science-map-.*\"}",
            "legendFormat": "{{job}}"
          }
        ],
        "gridPos": {"h": 8, "w": 12, "x": 12, "y": 0}
      },
      {
        "id": 3,
        "title": "Response Time",
        "type": "graph",
        "targets": [
          {
            "expr": "histogram_quantile(0.95, rate(http_request_duration_seconds_bucket[5m]))",
            "legendFormat": "95th percentile"
          },
          {
            "expr": "histogram_quantile(0.50, rate(http_request_duration_seconds_bucket[5m]))",
            "legendFormat": "50th percentile"
          }
        ],
        "gridPos": {"h": 8, "w": 24, "x": 0, "y": 8}
      },
      {
        "id": 4,
        "title": "Error Rate",
        "type": "graph",
        "targets": [
          {
            "expr": "rate(http_requests_total{status=~\"5..\"}[5m])",
            "legendFormat": "5xx errors"
          },
          {
            "expr": "rate(http_requests_total{status=~\"4..\"}[5m])",
            "legendFormat": "4xx errors"
          }
        ],
        "gridPos": {"h": 8, "w": 12, "x": 0, "y": 16}
      },
      {
        "id": 5,
        "title": "Memory Usage",
        "type": "graph",
        "targets": [
          {
            "expr": "process_resident_memory_bytes",
            "legendFormat": "{{job}}"
          }
        ],
        "gridPos": {"h": 8, "w": 12, "x": 12, "y": 16}
      },
      {
        "id": 6,
        "title": "CPU Usage",
        "type": "graph",
        "targets": [
          {
            "expr": "rate(process_cpu_seconds_total[5m]) * 100",
            "legendFormat": "{{job}} CPU %"
          }
        ],
        "gridPos": {"h": 8, "w": 12, "x": 0, "y": 24}
      },
      {
        "id": 7,
        "title": "Database Connections",
        "type": "graph",
        "targets": [
          {
            "expr": "database_connections_active",
            "legendFormat": "{{job}} active connections"
          }
        ],
        "gridPos": {"h": 8, "w": 12, "x": 12, "y": 24}
      },
      {
        "id": 8,
        "title": "Cache Hit Rate",
        "type": "graph",
        "targets": [
          {
            "expr": "rate(cache_hits_total[5m]) / rate(cache_requests_total[5m]) * 100",
            "legendFormat": "{{job}} cache hit rate %"
          }
        ],
        "gridPos": {"h": 8, "w": 24, "x": 0, "y": 32}
      }
    ],
    "time": {
      "from": "now-1h",
      "to": "now"
    },
    "refresh": "30s"
  }
}
